notifier_client/__init__.py
notifier_client/main.py
NotifierClient-0.1.2.dist-info/LICENSE
NotifierClient-0.1.2.dist-info/METADATA
NotifierClient-0.1.2.dist-info/WHEEL
NotifierClient-0.1.2.dist-info/top_level.txt
NotifierClient-0.1.2.dist-info/RECORD
