Metadata-Version: 2.1
Name: NotifierClient
Version: 0.1.2
Summary: Python client for QwhaleNotifier
Home-page: https://notifier.qwhale.ml
Author: Yehoyada.s
Author-email: hvuhsg6@gmail.com
License: MIT
Keywords: API,Client,Qwhale,qWhale,client,notification,application
Platform: UNKNOWN
Classifier: Development Status :: 3 - Alpha
Classifier: Intended Audience :: Developers
Classifier: Topic :: Software Development :: Build Tools
Classifier: License :: OSI Approved :: MIT License
Classifier: Programming Language :: Python :: 3.6
Classifier: Programming Language :: Python :: 3.7
Classifier: Programming Language :: Python :: 3.8
Requires-Dist: requests
